gctree/__init__.py
gctree/_version.py
gctree/branching_processes.py
gctree/cli.py
gctree/deduplicate.py
gctree/isotype.py
gctree/isotyping.py
gctree/mkconfig.py
gctree/mutation_model.py
gctree/phylip_parse.py
gctree/utils.py
gctree-4.3.0.dist-info/LICENSE
gctree-4.3.0.dist-info/METADATA
gctree-4.3.0.dist-info/WHEEL
gctree-4.3.0.dist-info/entry_points.txt
gctree-4.3.0.dist-info/top_level.txt
gctree-4.3.0.dist-info/RECORD
