Metadata-Version: 2.1
Name: gctree
Version: 4.3.0
Summary: phylogenetic inference of genotype-collapsed trees
Home-page: https://github.com/matsengrp/gctree
Author: Matsen Group
Author-email: ematsen@gmail.com
Classifier: Programming Language :: Python :: 3
Classifier: License :: OSI Approved :: GNU General Public License (GPL)
Classifier: Operating System :: OS Independent
Requires-Python: >=3.7
License-File: LICENSE
Requires-Dist: PyQt5
Requires-Dist: ete3
Requires-Dist: biopython
Requires-Dist: matplotlib
Requires-Dist: pandas
Requires-Dist: scipy
Requires-Dist: seaborn
Requires-Dist: multiset
Requires-Dist: frozendict
Requires-Dist: historydag >=1.2.0
